openai_pricing_api/__init__.py
openai_pricing_api/calculator.py
openai_pricing_api/models.py
openai_pricing_api/pricing.py
openai_pricing_api-0.1.0.dist-info/METADATA
openai_pricing_api-0.1.0.dist-info/WHEEL
openai_pricing_api-0.1.0.dist-info/licenses/LICENSE
openai_pricing_api-0.1.0.dist-info/RECORD
