Metadata-Version: 2.4
Name: openai-pricing-api
Version: 0.1.0
Summary: Simple and clean API for OpenAI model cost calculation and tracking with automatic pricing updates
Project-URL: Homepage, https://github.com/bes-dev/openai-pricing-api
Project-URL: Documentation, https://github.com/bes-dev/openai-pricing-api#readme
Project-URL: Repository, https://github.com/bes-dev/openai-pricing-api
Project-URL: Issues, https://github.com/bes-dev/openai-pricing-api/issues
Project-URL: Pricing API, https://bes-dev.github.io/openai-pricing-api/
Author-email: bes-dev <bes.dev@gmail.com>
License: Apache-2.0
License-File: LICENSE
Keywords: ai,api-pricing,billing,cost,cost-tracking,dall-e,gpt,llm,openai,pricing
Classifier: Development Status :: 3 - Alpha
Classifier: Intended Audience :: Developers
Classifier: License :: OSI Approved :: Apache Software License
Classifier: Programming Language :: Python :: 3
Classifier: Programming Language :: Python :: 3.10
Classifier: Programming Language :: Python :: 3.11
Classifier: Programming Language :: Python :: 3.12
Classifier: Topic :: Scientific/Engineering :: Artificial Intelligence
Classifier: Topic :: Software Development :: Libraries
Requires-Python: >=3.10
Requires-Dist: pydantic<3.0,>=2.0
Provides-Extra: dev
Requires-Dist: black>=23.0; extra == 'dev'
Requires-Dist: mypy>=1.0; extra == 'dev'
Requires-Dist: pytest-asyncio>=0.21; extra == 'dev'
Requires-Dist: pytest>=7.0; extra == 'dev'
Requires-Dist: ruff>=0.1; extra == 'dev'
